theramin/__init__.py
theramin/main.py
theramin/util.py
theramin-0.0.5.dist-info/LICENSE
theramin-0.0.5.dist-info/METADATA
theramin-0.0.5.dist-info/WHEEL
theramin-0.0.5.dist-info/top_level.txt
theramin-0.0.5.dist-info/RECORD
