Metadata-Version: 2.1
Name: theramin
Version: 0.0.5
Summary: A video-to-sound theramin
Home-page: https://github.com/thorwhalen/theramin
Author: Thor Whalen
License: mit
Platform: any
License-File: LICENSE
